treadle/__init__.py
treadle-0.0.1.dist-info/METADATA
treadle-0.0.1.dist-info/WHEEL
treadle-0.0.1.dist-info/RECORD
