Metadata-Version: 2.4
Name: treadle
Version: 0.0.1
Summary: Local development toolkit for Microsoft Fabric
Project-URL: repository, https://github.com/onnovalkering/treadle
License-Expression: MIT
Requires-Python: >=3.11
